genascii/__main__.py
genascii/about.py
genascii/consts.py
genascii/core.py
genascii/main.py
genascii/utils.py
genascii/data/alphabets.json
genascii/data/fonts/DejaVu Fonts License.txt
genascii/data/fonts/DejaVuSansMono-BoldOblique_subset.ttf
genascii/data/fonts/DejaVuSansMono-Bold_subset.ttf
genascii/data/fonts/DejaVuSansMono-Oblique_subset.ttf
genascii/data/fonts/DejaVuSansMono_subset.ttf
genascii/data/fonts/arial-unicode_subset.ttf
genascii/data/fonts/simsun_subset.ttc
genascii-0.0.3.dist-info/LICENSE
genascii-0.0.3.dist-info/METADATA
genascii-0.0.3.dist-info/WHEEL
genascii-0.0.3.dist-info/top_level.txt
genascii-0.0.3.dist-info/RECORD
