Metadata-Version: 2.1
Name: genascii
Version: 0.0.3
Summary: Generate ASCII from images
Author-email: Viet Nguyen <nhviet1009@gmail.com>, brightsunshine0917 <brightsunshine0917@email.email>
License: MIT License
Project-URL: Homepage, https://github.com/brightsunshine0917/ASCII-generator.git
Classifier: License :: OSI Approved :: MIT License
Classifier: Operating System :: OS Independent
Classifier: Programming Language :: Python
Classifier: Programming Language :: Python :: 3.12
Classifier: Programming Language :: Python :: 3.13
Classifier: Programming Language :: Python :: 3 :: Only
Requires-Python: >=3.12
License-File: LICENSE
Requires-Dist: numpy==2.1.3
Requires-Dist: opencv-python==4.10.0.84
Requires-Dist: pillow==11.0.0
